aestools-0.1.1.dist-info/metadata.json
aestools-0.1.1.dist-info/entry_points.txt
aestools-0.1.1.dist-info/METADATA
aestools-0.1.1.dist-info/DESCRIPTION.rst
aestools-0.1.1.dist-info/top_level.txt
aestools-0.1.1.dist-info/RECORD
aestools-0.1.1.dist-info/WHEEL
aestools/__init__.py
aestools/checkkey.py
aestools/safekey.py
aestools/cli.py
aestools/_tests/test_safekey.py
aestools/_tests/__init__.py
aestools/_tests/test_checkkey.py
