Metadata-Version: 2.0
Name: aestools
Version: 0.1.1
Summary: AES tools (GCM weak key checker / safe key generator)
Home-page: https://github.com/lichtkegel/aestools
Author: Jesko Hüttenhain
Author-email: rattle@nullteilerfrei.de
License: PSF License
Keywords: crypto aes gcm weak key checker safe key generator
Platform: any
Classifier: Development Status :: 3 - Alpha
Classifier: Environment :: Console
Classifier: Intended Audience :: Developers
Classifier: Intended Audience :: Science/Research
Classifier: License :: OSI Approved :: Python Software Foundation License
Classifier: Operating System :: OS Independent
Classifier: Programming Language :: Python
Classifier: Programming Language :: Python :: 2
Classifier: Programming Language :: Python :: 2.7
Classifier: Programming Language :: Python :: 3
Classifier: Programming Language :: Python :: 3.4
Classifier: Programming Language :: Python :: 3.5
Classifier: Topic :: Security :: Cryptography
Requires-Dist: pycrypto
